altb_utils/__init__.py
altb_utils/_version.py
altb_utils/utils.py
altb_utils-0.0.11.dist-info/METADATA
altb_utils-0.0.11.dist-info/WHEEL
altb_utils-0.0.11.dist-info/top_level.txt
altb_utils-0.0.11.dist-info/RECORD
